[
  {
    "name": "MetaMask",
    "logo": "https://upload.wikimedia.org/wikipedia/commons/3/36/MetaMask_Fox.svg"
  },
  {
    "name": "Trust Wallet",
    "logo": "https://trustwallet.com/assets/images/media/assets/TWT.png"
  },
  {
    "name": "Coinbase Wallet",
    "logo": "static/logos/coinbase.svg"
  },
  {
    "name": "Phantom",
    "logo": "static/logos/Phantom.svg"
  },
  {
    "name": "Rainbow",
    "logo": "static/logos/Rainbow.png"
  },
  {
    "name": "Zengo",
    "logo": "static/logos/zengo.png"
  },
  {
    "name": "Rabby Wallet",
    "logo": "static/logos/rabby.jpeg"
  },
  {
    "name": "Binance Wallet",
    "logo": "static/logos/Binance.svg"
  },
  {
    "name": "Crypto.com DeFi Wallet",
    "logo": "static/logos/crypto_com.jpeg"
  },
  {
    "name": "1inch Wallet",
    "logo": "https://1inch.io/img/logo.svg"
  },
  {
    "name": "Backpack",
    "logo": "static/logos/backpack.jpeg"
  },
  {
    "name": "Ledger Live",
    "logo": "static/logos/ledger.svg"
  },
  {
    "name": "MathWallet",
    "logo": "static/logos/mathwallet.png"
  },
  {
    "name": "iToken Wallet",
    "logo": "static/logos/itoken.jpeg"
  },
  {
    "name": "Huddln",
    "logo": "https://huddln.io/assets/logo.png"
  },
  {
    "name": "Eidoo",
    "logo": "https://eidoo.io/images/eidoo-logo.svg"
  },
  {
    "name": "Timeless Wallet",
    "logo": "https://timelesswallet.com/assets/logo.png"
  },
  {
    "name": "CoolWallet",
    "logo": "https://coolwallet.io/wp-content/uploads/2021/05/coolwallet-logo.svg"
  },
  {
    "name": "Unstoppable Wallet",
    "logo": "https://unstoppablewallet.com/assets/logo.png"
  },
  {
    "name": "AlphaWallet",
    "logo": "https://alphawallet.com/assets/logo.png"
  },
  {
    "name": "Pillar",
    "logo": "https://pillarproject.io/assets/logo.png"
  },
  {
    "name": "D'CENT Wallet",
    "logo": "https://dcentwallet.com/assets/logo.png"
  },
  {
    "name": "ZelCore",
    "logo": "https://zelcore.io/assets/logo.png"
  },
  {
    "name": "Nash",
    "logo": "https://nash.io/assets/logo.png"
  },
  {
    "name": "Coinomi",
    "logo": "https://coinomi.com/assets/logo.png"
  },
  {
    "name": "CYBAVO Wallet",
    "logo": "https://cybavo.com/assets/logo.png"
  },
  {
    "name": "Tokenary",
    "logo": "https://tokenary.io/assets/logo.png"
  },
  {
    "name": "Torus",
    "logo": "https://tor.us/images/torus-logo.svg"
  },
  {
    "name": "Keplr Wallet",
    "logo": "https://wallet.keplr.app/assets/logo.png"
  },
  {
    "name": "Leap Wallet",
    "logo": "https://leapwallet.io/assets/logo.png"
  },
  {
    "name": "World App",
    "logo": "https://worldapp.com/assets/logo.png"
  },
  {
    "name": "BitPay",
    "logo": "https://bitpay.com/images/bitpay-logo.svg"
  },
  {
    "name": "SafePal",
    "logo": "https://safepal.io/assets/logo.png"
  },
  {
    "name": "Argent",
    "logo": "https://argent.xyz/assets/logo.png"
  },
  {
    "name": "Gnosis Safe",
    "logo": "https://gnosis-safe.io/assets/logo.png"
  },
  {
    "name": "Trezor Suite",
    "logo": "https://trezor.io/assets/logo.png"
  },
  {
    "name": "Exodus",
    "logo": "https://www.exodus.com/assets/logo.png"
  },
  {
    "name": "MyEtherWallet",
    "logo": "https://www.myetherwallet.com/images/logo.svg"
  },
  {
    "name": "Atomic Wallet",
    "logo": "https://atomicwallet.io/assets/logo.png"
  },
  {
    "name": "Edge Wallet",
    "logo": "https://edge.app/assets/logo.png"
  }
]
